decorstate.py
decorstate-0.0.3.dist-info/top_level.txt
decorstate-0.0.3.dist-info/METADATA
decorstate-0.0.3.dist-info/DESCRIPTION.rst
decorstate-0.0.3.dist-info/LICENSE.txt
decorstate-0.0.3.dist-info/metadata.json
decorstate-0.0.3.dist-info/WHEEL
decorstate-0.0.3.dist-info/RECORD
